rhdash/__init__.py
rhdash/alg.py
rhdash/app.py
rhdash/args.py
rhdash/config.py
rhdash/rh.py
rhdash/rhdash.py
rhdash-0.1.13.dist-info/entry_points.txt
rhdash-0.1.13.dist-info/WHEEL
rhdash-0.1.13.dist-info/METADATA
rhdash-0.1.13.dist-info/RECORD
